persistable/__init__.py
persistable/base.py
persistable/data.py
persistable/exceptions.py
persistable/io.py
persistable/logging.py
persistable-1.3.1.dist-info/METADATA
persistable-1.3.1.dist-info/WHEEL
persistable-1.3.1.dist-info/licenses/LICENSE
persistable-1.3.1.dist-info/RECORD
