Metadata-Version: 2.4
Name: persistable
Version: 1.3.1
Summary: Reproducible parameter based pipelines and persisting
Project-URL: Repository, https://github.com/aloosley/persistable
Author-email: Alexander Loosley <aloosley@alumni.brown.edu>, Stephan Sahm <Stephan.Sahm@gmx.de>
License-File: LICENSE
Keywords: models,persisting,pipeline
Classifier: Intended Audience :: Developers
Classifier: Programming Language :: Python :: 3
Requires-Python: >=3.9
Requires-Dist: numpy>=1.21.0
